csv_collate/__init__.py
csv_collate/collate.py
ncl_csv_collate-1.3.0.dist-info/LICENSE
ncl_csv_collate-1.3.0.dist-info/METADATA
ncl_csv_collate-1.3.0.dist-info/WHEEL
ncl_csv_collate-1.3.0.dist-info/top_level.txt
ncl_csv_collate-1.3.0.dist-info/RECORD
