Metadata-Version: 2.1
Name: ncl_csv_collate
Version: 1.3.0
Summary: Module to collate loose csv files with export options
Author-email: Jake Kealey <jake.kealey@nhs.net>
Project-URL: Homepage, https://github.com/ncl-icb-analytics/csv_collate
Project-URL: Issues, https://github.com/ncl-icb-analytics/csv_collate/issues
Classifier: Programming Language :: Python :: 3
Classifier: License :: OSI Approved :: MIT License
Classifier: Operating System :: OS Independent
Requires-Python: >=3.9
License-File: LICENSE
Requires-Dist: pandas >=2.1.4
Requires-Dist: SQLAlchemy >=2.0.5.post1
Requires-Dist: ncl-sqlsnippets >=1.2.3
